tempora/__init__.py
tempora/schedule.py
tempora/timing.py
tempora/utc.py
tempora-5.7.0.dist-info/LICENSE
tempora-5.7.0.dist-info/METADATA
tempora-5.7.0.dist-info/WHEEL
tempora-5.7.0.dist-info/entry_points.txt
tempora-5.7.0.dist-info/top_level.txt
tempora-5.7.0.dist-info/RECORD
