Metadata-Version: 2.1
Name: tempora
Version: 5.7.0
Summary: Objects and routines pertaining to date and time (tempora)
Author-email: "Jason R. Coombs" <jaraco@jaraco.com>
Project-URL: Source, https://github.com/jaraco/tempora
Classifier: Development Status :: 5 - Production/Stable
Classifier: Intended Audience :: Developers
Classifier: License :: OSI Approved :: MIT License
Classifier: Programming Language :: Python :: 3
Classifier: Programming Language :: Python :: 3 :: Only
Requires-Python: >=3.8
License-File: LICENSE
Requires-Dist: jaraco.functools>=1.20
Requires-Dist: python-dateutil
Provides-Extra: test
Requires-Dist: pytest!=8.1.*,>=6; extra == "test"
Requires-Dist: pytest-checkdocs>=2.4; extra == "test"
Requires-Dist: pytest-cov; extra == "test"
Requires-Dist: pytest-mypy; extra == "test"
Requires-Dist: pytest-enabler>=2.2; extra == "test"
Requires-Dist: pytest-ruff>=0.2.1; sys_platform != "cygwin" and extra == "test"
Requires-Dist: pytest-freezer; extra == "test"
Requires-Dist: backports.zoneinfo; python_version < "3.9" and extra == "test"
Requires-Dist: tzdata; platform_system == "Windows" and extra == "test"
Requires-Dist: types-python-dateutil; extra == "test"
Provides-Extra: doc
Requires-Dist: sphinx>=3.5; extra == "doc"
Requires-Dist: jaraco.packaging>=9.3; extra == "doc"
Requires-Dist: rst.linker>=1.9; extra == "doc"
Requires-Dist: furo; extra == "doc"
Requires-Dist: sphinx-lint; extra == "doc"
Requires-Dist: jaraco.tidelift>=1.4; extra == "doc"
